orquestaconvert/__init__.py
orquestaconvert/client.py
orquestaconvert/pack_client.py
orquestaconvert/expressions/__init__.py
orquestaconvert/expressions/base.py
orquestaconvert/expressions/jinja.py
orquestaconvert/expressions/mixed.py
orquestaconvert/expressions/yaql.py
orquestaconvert/utils/__init__.py
orquestaconvert/utils/task_utils.py
orquestaconvert/utils/type_utils.py
orquestaconvert/utils/yaml_utils.py
orquestaconvert/workflows/__init__.py
orquestaconvert/workflows/base.py
orquestaconvert-0.1.data/scripts/orquestaconvert-pack.sh
orquestaconvert-0.1.data/scripts/orquestaconvert.sh
tests/integration/__init__.py
tests/integration/test_convert_pack.py
tests/integration/test_end_to_end.py
tests/unit/__init__.py
tests/unit/test_client.py
tests/unit/test_expressions.py
tests/unit/test_expressions_base.py
tests/unit/test_expressions_jinja.py
tests/unit/test_expressions_mixed.py
tests/unit/test_expressions_yaql.py
tests/unit/test_pack_client.py
tests/unit/test_utils_task_utils.py
tests/unit/test_utils_type_utils.py
tests/unit/test_utils_yaml_utils.py
tests/unit/test_workflows.py
orquestaconvert-0.1.dist-info/LICENSE
orquestaconvert-0.1.dist-info/METADATA
orquestaconvert-0.1.dist-info/WHEEL
orquestaconvert-0.1.dist-info/dependency_links.txt
orquestaconvert-0.1.dist-info/top_level.txt
orquestaconvert-0.1.dist-info/RECORD
