Metadata-Version: 2.1
Name: orquestaconvert
Version: 0.1
Summary: Tool to convert OpenStack Mistral workflows to StackStorm Orquesta workflows
Home-page: https://encore.tech/
Author: Encore Technologies
Author-email: code@encore.tech
License: UNKNOWN
Platform: UNKNOWN
Classifier: Development Status :: 3 - Alpha
Classifier: License :: OSI Approved :: Apache Software License
Classifier: Programming Language :: Python
Classifier: Programming Language :: Python :: 3
Classifier: Programming Language :: Python :: 3.5
Classifier: Programming Language :: Python :: 3.6
Classifier: Programming Language :: Python :: 3.7
Classifier: Programming Language :: Python :: 3.8
Classifier: Intended Audience :: Developers
Classifier: Environment :: Console
Requires-Dist: ruamel.yaml (>=0.15.0)
Requires-Dist: yamlloader (>=0.5.0)
Requires-Dist: orquesta
